musdb/__init__.py
musdb/audio_classes.py
musdb/tools.py
musdb/version.py
musdb/configs/mus.yaml
musdb-0.4.3.dist-info/licenses/LICENSE
musdb-0.4.3.dist-info/METADATA
musdb-0.4.3.dist-info/WHEEL
musdb-0.4.3.dist-info/entry_points.txt
musdb-0.4.3.dist-info/top_level.txt
musdb-0.4.3.dist-info/RECORD
